TwoD_Form_Finding.py
TwoD_Form_Finding-1.0.7.dist-info/LICENSE
TwoD_Form_Finding-1.0.7.dist-info/METADATA
TwoD_Form_Finding-1.0.7.dist-info/WHEEL
TwoD_Form_Finding-1.0.7.dist-info/top_level.txt
TwoD_Form_Finding-1.0.7.dist-info/RECORD
